<?xml version="1.0" encoding="utf-8" ?>
<dwsync>
<file name="chematix_template.xlsx" server="ar08.uky.edu//ehs/" local="131628463343150491" remote="131279796000000000" Dst="1" />
<file name="php_logo_1.png" server="ar08.uky.edu//ehs/" local="131628463344774760" remote="131279796000000000" Dst="1" />
<file name="uk_logo_1.png" server="ar08.uky.edu//ehs/" local="131628463411606337" remote="131279796000000000" Dst="1" />
<file name="chematix_user_guide.pdf" server="ar08.uky.edu//ehs/" local="131628463432231708" remote="131279796000000000" Dst="1" />
<file name="chematix_template.xlsx" server="arftp.ad.uky.edu//ehs/apps/mendeleev/" local="131628485858074015" remote="131628309000000000" Dst="1" />
<file name="chematix_user_guide.pdf" server="arftp.ad.uky.edu//ehs/apps/mendeleev/" local="131628485858535333" remote="131628309600000000" Dst="1" />
<file name="php_logo_1.png" server="arftp.ad.uky.edu//ehs/apps/mendeleev/" local="131628485858605448" remote="131628309600000000" Dst="1" />
<file name="uk_logo_1.png" server="arftp.ad.uky.edu//ehs/apps/mendeleev/" local="131628485858715734" remote="131628309600000000" Dst="1" />
</dwsync>